[
  {
    "kotoba": "痔核",
    "yomi": "じ‐かく",
    "link": "/word/%E7%97%94%E6%A0%B8/#jn-94350"
  },
  {
    "kotoba": "地気",
    "yomi": "ち‐き",
    "link": "/word/%E5%9C%B0%E6%B0%97/#jn-141312"
  },
  {
    "kotoba": "痔血",
    "yomi": "じ‐けつ",
    "link": "/word/%E7%97%94%E8%A1%80/#jn-95509"
  },
  {
    "kotoba": "痔疾",
    "yomi": "じ‐しつ",
    "link": "/word/%E7%97%94%E7%96%BE/#jn-96191"
  },
  {
    "kotoba": "地神",
    "yomi": "ち‐じん",
    "link": "/word/%E5%9C%B0%E7%A5%9E_%28%E3%81%A1%E3%81%98%E3%82%93%29/#jn-141758"
  },
  {
    "kotoba": "帙簀",
    "yomi": "ち‐す",
    "link": "/word/%E5%B8%99%E7%B0%80/#jn-141767"
  },
  {
    "kotoba": "地府",
    "yomi": "ち‐ふ",
    "link": "/word/%E5%9C%B0%E5%BA%9C/#jn-142221"
  },
  {
    "kotoba": "地味",
    "yomi": "ち‐み",
    "link": "/word/%E5%9C%B0%E5%91%B3_%28%E3%81%A1%E3%81%BF%29/#jn-142362"
  },
  {
    "kotoba": "着心",
    "yomi": "ちゃく‐しん",
    "link": "/word/%E7%9D%80%E5%BF%83_%28%E3%81%A1%E3%82%83%E3%81%8F%E3%81%97%E3%82%93%29/#jn-142554"
  },
  {
    "kotoba": "着相",
    "yomi": "ちゃく‐そう",
    "link": "/word/%E7%9D%80%E7%9B%B8/#jn-142567"
  },
  {
    "kotoba": "地楡",
    "yomi": "ち‐ゆ",
    "link": "/word/%E5%9C%B0%E6%A5%A1/#jn-142920"
  },
  {
    "kotoba": "長講",
    "yomi": "ちょう‐こう",
    "link": "/word/%E9%95%B7%E8%AC%9B/#jn-144157"
  },
  {
    "kotoba": "鑷子",
    "yomi": "ちょう‐し",
    "link": "/word/%E9%91%B7%E5%AD%90_%28%E3%81%A1%E3%82%87%E3%81%86%E3%81%97%29/#jn-144264"
  },
  {
    "kotoba": "朝夕",
    "yomi": "ちょう‐じゃく",
    "link": "/word/%E6%9C%9D%E5%A4%95_%28%E3%81%A1%E3%82%87%E3%81%86%E3%81%98%E3%82%83%E3%81%8F%29/#jn-144325"
  },
  {
    "kotoba": "調度",
    "yomi": "ちょう‐ど",
    "link": "/word/%E8%AA%BF%E5%BA%A6/#jn-144698"
  },
  {
    "kotoba": "調伏",
    "yomi": "ちょう‐ぶく",
    "link": "/word/%E8%AA%BF%E4%BC%8F/#jn-144805"
  },
  {
    "kotoba": "長夜",
    "yomi": "ちょう‐や",
    "link": "/word/%E9%95%B7%E5%A4%9C_%28%E3%81%A1%E3%82%87%E3%81%86%E3%82%84%29/#jn-144906"
  },
  {
    "kotoba": "治略",
    "yomi": "ち‐りゃく",
    "link": "/word/%E6%B2%BB%E7%95%A5/#jn-145536"
  },
  {
    "kotoba": "治療",
    "yomi": "ち‐りょう",
    "link": "/word/%E6%B2%BB%E7%99%82/#jn-145543"
  },
  {
    "kotoba": "地類",
    "yomi": "ち‐るい",
    "link": "/word/%E5%9C%B0%E9%A1%9E_%28%E3%81%A1%E3%82%8B%E3%81%84%29/#jn-145558"
  },
  {
    "kotoba": "地炉",
    "yomi": "ち‐ろ",
    "link": "/word/%E5%9C%B0%E7%82%89_%28%E3%81%A1%E3%82%8D%29/#jn-145576"
  },
  {
    "kotoba": "痔瘻",
    "yomi": "じ‐ろう",
    "link": "/word/%E7%97%94%E7%98%BB/#jn-112919"
  }
]